Metadata-Version: 1.0
Name: distributions-package-iamanshika
Version: 0.1
Summary: Gaussian distributions
Home-page: UNKNOWN
Author: Anshika Gupta
Author-email: iamanshika19@gmail.com
License: UNKNOWN
Platform: UNKNOWN
